{
  "parent": "minecraft:minecard/root",
  "criteria": {
    "iron_golem_farm": {
      "conditions": {
        "id": "minecard:iron_golem_farm"
      },
      "trigger": "minecard:game"
    }
  },
  "display": {
    "announce_to_chat": true,
    "description": {
      "translate": "advancements.minecard.iron_golem_farm.description"
    },
    "frame": "goal",
    "hidden": false,
    "icon": {
      "item": "minecraft:iron_ingot"
    },
    "show_toast": true,
    "title": {
      "translate": "advancements.minecard.iron_golem_farm.title"
    }
  },
  "requirements": [
    [
      "iron_golem_farm"
    ]
  ]
}