{
  "abilities": {
    "type": "minecard:chain",
    "value": {
      "triggers": [
        "hurt"
      ],
      "text_key": "card_ability.minecard.axolotl",
      "abilities": [
        {
          "type": "minecard:select_cards",
          "value": {
            "selection": {
              "groups": [
                "self"
              ],
              "method": {
                "type": "minecard:all"
              }
            }
          }
        },
        {
          "type": "minecard:modify",
          "value": {
            "modifications": [
              [
                {
                  "output": {
                    "type": "minecard:property",
                    "value": "minecard:stealth"
                  },
                  "operator": {
                    "type": "minecard:constant",
                    "value": 1
                  }
                }
              ]
            ]
          }
        }
      ]
    }
  },
  "entity": "minecraft:axolotl",
  "cost": 2,
  "health": 4,
  "damage": 1
}